nrql/__init__.py
nrql/__main__.py
nrql/api.py
nrql/cli.py
nrql/utils.py
nrql_cli-1.0.3.dist-info/METADATA
nrql_cli-1.0.3.dist-info/WHEEL
nrql_cli-1.0.3.dist-info/entry_points.txt
nrql_cli-1.0.3.dist-info/top_level.txt
nrql_cli-1.0.3.dist-info/RECORD
