Metadata-Version: 2.1
Name: nrql-cli
Version: 1.0.3
Summary: An interactive command line interface for querying NRQL data.
Home-page: https://github.com/anthonybloomer/nrql-cli
Author: Anthony Bloomer
Author-email: ant0@protonmail.ch
License: MIT
Platform: UNKNOWN
Classifier: License :: OSI Approved :: MIT License
Classifier: Programming Language :: Python
Requires-Python: >=3.7.0
Requires-Dist: requests
Requires-Dist: colorful
Requires-Dist: halo
Requires-Dist: prompt-toolkit
Requires-Dist: pygments
